alg_etf/__init__.py
alg_etf/__init__.pyi
alg_etf/_core.pypy39-pp73-s390x-linux-gnu.so
alg_etf-0.1.2.dist-info/METADATA
alg_etf-0.1.2.dist-info/WHEEL
alg_etf-0.1.2.dist-info/entry_points.txt
alg_etf-0.1.2.dist-info/RECORD
