Metadata-Version: 2.4
Name: alg_etf
Version: 0.1.2
Summary: analog layout generator using rust backend mainly for etf layouts
Author-email: Tim van den Akker <timakk01@gmail.com>
Requires-Python: >=3.9.0
